{
  "/checkout/page": "app/checkout/page.js",
  "/cart/page": "app/cart/page.js",
  "/_not-found/page": "app/_not-found/page.js",
  "/page": "app/page.js",
  "/product/[id]/page": "app/product/[id]/page.js",
  "/shop/page": "app/shop/page.js",
  "/wishlist/page": "app/wishlist/page.js",
  "/blog/page": "app/blog/page.js",
  "/careers/page": "app/careers/page.js",
  "/contact/page": "app/contact/page.js",
  "/faq/page": "app/faq/page.js",
  "/privacy/page": "app/privacy/page.js",
  "/shipping/page": "app/shipping/page.js",
  "/about/page": "app/about/page.js",
  "/size-guide/page": "app/size-guide/page.js",
  "/sustainability/page": "app/sustainability/page.js",
  "/terms/page": "app/terms/page.js",
  "/collections/page": "app/collections/page.js"
}